{"summary":"\u0422\u044b \u043f\u043e\u043b\u0443\u0447\u0438\u043b \u043d\u0438\u0448\u0442\u044f\u0447\u0435\u043a \u043e\u0442 Clubnika\ud83c\udf81","location":"Ukraine, Kiev","description":"<div class=\"plbazxn\"><h1 style=\"text-align: center;\">\ud83e\udd11 \u0412\u0430\u043c \u043f\u043e\u0434\u0430\u0440\u043e\u043a \u043e\u0442 Clubnika <\/h1><\/div><div style=\"text-align: center;\">\u0416\u0435\u043b\u0430\u0435\u0448\u044c \u043e\u0442\u0442\u044f\u043d\u0443\u0442\u044c\u0441\u044f \u0441 \u0430\u0437\u0430\u0440\u0442\u043e\u043c \u0432\u043c\u0435\u0441\u0442\u0435 \u0441 Clubnika\u265b?<\/div>\r\n<\/div><div class=\"xnvn\"><div style=\"text-align: center;\"><h3>\u0422\u044b \u0442\u043e\u0440\u0436\u0435\u0441\u0442\u0432\u0435\u043d\u043d\u043e \u043f\u043e\u043b\u0443\u0447\u0430\u0435\u0448\u044c 150% \u043a \u0441\u0443\u043c\u043c\u0435 \u0434\u0435\u043f\u043e\u0437\u0438\u0442\u0430!<\/h3>\r\n<center>\u2714\ufe0f \u0422\u044b \u043f\u043e\u043b\u0443\u0447\u0438\u043b \u043f\u043e\u0434\u0433\u043e\u043d +150% \u043a \u0442\u0432\u043e\u0435\u043c\u0443 \u0434\u0435\u043f\u0447\u0438\u043a\u0443<\/center>\r\n<center>\u2714\ufe0f MAX \u0441\u0443\u043c\u043c\u0430 \u0431\u043e\u043d\u0443\u0441\u0430 50k \u0440\u0443\u0431\u043b\u0435\u0439<\/center>\r\n<center>\u2714\ufe0f \u041c\u0438\u043d\u0438\u043c\u0430\u043b\u044c\u043d\u044b\u0439 \u0434\u0435\u043f. 500 \u0440\u0443\u0431<\/center>\r\n<center>\u2714\ufe0f \u0411\u0435\u0441\u043f\u043b\u0430\u0442\u043d\u044b\u0435 \u0441\u043f\u0438\u043d\u044b \u0432 \u0422\u0432\u043e\u0438\u0445 \u043b\u044e\u0431\u0438\u043c\u044b\u0445 \u0430\u0432\u0442\u043e\u043c\u0430\u0442\u0430\u0445!<\/center>\r\n<center>\u2714\ufe0f \u041c\u043d\u043e\u0436\u0438\u0442\u0435\u043b\u044c (wager) x35<\/center><\/div><\/div><div class=\"kkxo\" style=\"text-align: center;\"><div>\u041d\u0438\u0448\u0442\u044f\u043a \u043e\u0442\u043e\u0431\u0440\u0430\u0437\u0438\u0442\u0441\u044f, \u0434\u043b\u044f <strong>\u043f\u043e\u043b\u0443\u0447\u0435\u043d\u0438\u044f \u0438 \u0430\u043a\u0442\u0438\u0432\u0430\u0446\u0438\u0438<\/strong> \u043f\u0440\u043e\u0441\u0442\u043e \u043a\u043b\u0438\u043a\u0430\u0439 \u043f\u043e \u0443\u043a\u0430\u0437\u0430\u043d\u043d\u043e\u0439 \u0441\u0441\u044b\u043b\u043a\u0435<\/div><\/div><div class=\"njnjiy\"><blockquote><div style=\"text-align: center;\"><span style=\"text-decoration: underline;\"><strong><a href=\"https:\/\/kazinovipwin.xyz\/axgza?new=0\">\u0416\u041c\u0418 \ud83d\udcb8\ud83c\udf81\ud83d\udcb8 \u041f\u041e\u041b\u0423\u0427\u0418\u0422\u042c \u0422\u0412\u041e\u0419 \u041f\u041e\u0414\u0410\u0420\u041e\u041a&nbsp;\ud83d\udc49\ud83d\udc49kazinovipwin.xyz <\/a><\/strong><\/span><\/div><\/blockquote><\/div><div class=\"unek\"><div><h2 style=\"text-align: center;\">\ud83d\udcb8\u0411\u0435\u0437\u0434\u0435\u043f\u044b \u0434\u043b\u044f \u043d\u043e\u0432\u0438\u0447\u043a\u043e\u0432\ud83c\udf81<\/h2><div><blockquote><div style=\"text-align: center;\"><em>\u041f\u0440\u0438\u0441\u043e\u0435\u0434\u0438\u043d\u044f\u0439\u0441\u044f \u043a \u041a\u043b\u0443\u0431\u043d\u0438\u043a\u0435 \u043f\u0440\u044f\u043c\u043e \u0441\u0435\u0439\u0447\u0430\u0441 \u0438 \u0422\u044b \u043d\u0435 \u043f\u043e\u0436\u0430\u043b\u0435\u0435\u0448\u044c!!<\/em><\/div><\/blockquote><\/div><p  style=\"text-align: center;\">\ud83e\udd11 \u0414\u0430\u0440\u0438\u043c \u0432\u0441\u0435\u043c \u043d\u043e\u0432\u044b\u043c \u0438\u0433\u0440\u043e\u043a\u0430\u043c <strong>350 \u0431\u0435\u0441\u043f\u043b\u0430\u0442\u043d\u044b\u0445 \u0432\u0440\u0430\u0449\u0435\u043d\u0438\u0439<\/strong> \u0432 \u0441\u0430\u043c\u044b\u0445 \u043b\u0443\u0447\u0448\u0438\u0445 \u0441\u043b\u043e\u0442\u0430\u0445<\/p><p class=\"bbliii\" style=\"text-align: center;\">\ud83c\udf81 \u0420\u0435\u0433\u0438\u0441\u0442\u0440\u0438\u0440\u0443\u0439\u0441\u044f \u0441\u0435\u0439\u0447\u0430\u0441 \u0438 \u0437\u0430\u0431\u0438\u0440\u0430\u0439 <strong>\u0431\u043e\u043d\u0443\u0441 \u043a \u043f\u0435\u0440\u0432\u043e\u043c\u0443 \u0434\u0435\u043f\u043e\u0437\u0438\u0442\u0443 +400% <br \/><\/strong><\/p><blockquote><div style=\"text-align: center;\"><a href=\"https:\/\/kazino-vipwin.xyz\/aaaana?old=0\">\ud83d\udc49\ud83d\udc49\ud83d\udc49 \u041f\u0415\u0420\u0415\u0419\u0422\u0418 \u041a \u0420\u0415\u0413\u0418\u0421\u0422\u0420\u0410\u0426\u0418\u0418&nbsp;\ud83d\udc49\ud83d\udc49kazino-vipwin.xyz<\/a><\/div><\/blockquote><\/div><\/div>","start":{"dateTime":"2021-10-01T19:09:49","timeZone":"Europe\/Kiev"},"end":{"dateTime":"2021-10-01T20:09:22","timeZone":"Europe\/Kiev"},"attendees":[{"email":"flex150db@gmail.com","responseStatus":"accepted"},{"email":"www.eg.28@gmail.com","responseStatus":"accepted"},{"email":"rusl.pq1612@gmail.com","responseStatus":"accepted"},{"email":"scharafutdinova.olia@gmail.com","responseStatus":"accepted"},{"email":"harsus0843@gmail.com","responseStatus":"accepted"},{"email":"slava.gordeik@gmail.com","responseStatus":"accepted"},{"email":"princessa55528@gmail.com","responseStatus":"accepted"},{"email":"kozhukhin45544@gmail.com","responseStatus":"accepted"},{"email":"kurilin395@gmail.com","responseStatus":"accepted"},{"email":"Dumler26@gmail.com","responseStatus":"accepted"},{"email":"prank7k@gmail.com","responseStatus":"accepted"},{"email":"vvvlfl@gmail.com","responseStatus":"accepted"},{"email":"carlosalvarez220849@gmail.com","responseStatus":"accepted"},{"email":"nikitagybin.hpb@gmail.com","responseStatus":"accepted"},{"email":"sorokinanatala544@gmail.com","responseStatus":"accepted"},{"email":"Egor85.g@gmail.com","responseStatus":"accepted"},{"email":"Usmanovasabi44@gmail.com","responseStatus":"accepted"},{"email":"dadabaev244@gmail.com","responseStatus":"accepted"},{"email":"ixrystin@gmail.com","responseStatus":"accepted"},{"email":"tacsen@gmail.com","responseStatus":"accepted"},{"email":"kuzinika677@gmail.com","responseStatus":"accepted"},{"email":"ayaalpakhomov2004@gmail.com","responseStatus":"accepted"},{"email":"ivansolodkov71979@gmail.com","responseStatus":"accepted"},{"email":"ss5985980@gmail.com","responseStatus":"accepted"},{"email":"zaicewa.ps.330@gmail.com","responseStatus":"accepted"},{"email":"debbiebunkin@gmail.com","responseStatus":"accepted"},{"email":"Dumas111w@gmail.com","responseStatus":"accepted"},{"email":"andreigubenko1@gmail.com","responseStatus":"accepted"},{"email":"andrejsemencuk30@gmail.com","responseStatus":"accepted"},{"email":"skif978@gmail.com","responseStatus":"accepted"},{"email":"ffffffff6dgbc9@gmail.com","responseStatus":"accepted"},{"email":"gubeman230@gmail.com","responseStatus":"accepted"},{"email":"slavikira@gmail.com","responseStatus":"accepted"},{"email":"susana196867@gmail.com","responseStatus":"accepted"},{"email":"strike281080@gmail.com","responseStatus":"accepted"},{"email":"safronka12366@gmail.com","responseStatus":"accepted"},{"email":"ns090683@gmail.com","responseStatus":"accepted"},{"email":"kez1231992@gmail.com","responseStatus":"accepted"},{"email":"kanal.athur@gmail.com","responseStatus":"accepted"},{"email":"ib439221@gmail.com","responseStatus":"accepted"},{"email":"arsentolokov17@gmail.com","responseStatus":"accepted"},{"email":"kek23456789@gmail.com","responseStatus":"accepted"},{"email":"kuzmievgenij1985@gmail.com","responseStatus":"accepted"},{"email":"borisotih7@gmail.com","responseStatus":"accepted"},{"email":"ivanabrikos.2004@gmail.com","responseStatus":"accepted"},{"email":"napaslavandospapiros@gmail.com","responseStatus":"accepted"},{"email":"cherndenisik@gmail.com","responseStatus":"accepted"},{"email":"Alexburavov0812@gmail.com","responseStatus":"accepted"},{"email":"shishov2408@gmail.com","responseStatus":"accepted"},{"email":"nat.kos97@gmail.com","responseStatus":"accepted"},{"email":"valentinpominchuk@gmail.com","responseStatus":"accepted"},{"email":"Madlen8914@gmail.com","responseStatus":"accepted"},{"email":"laurapetrova63@gmail.com","responseStatus":"accepted"},{"email":"0796987@gmail.com","responseStatus":"accepted"},{"email":"dima04038142@gmail.com","responseStatus":"accepted"},{"email":"Sk0794@gmail.com","responseStatus":"accepted"},{"email":"magam5753@gmail.com","responseStatus":"accepted"},{"email":"korol.larikov1998@gmail.com","responseStatus":"accepted"},{"email":"dajyroverzan058@gmail.com","responseStatus":"accepted"},{"email":"Olawaleolapeju58@gmail.com","responseStatus":"accepted"},{"email":"mehroj29.5.1997@gmail.com","responseStatus":"accepted"},{"email":"demon1988888888@gmail.com","responseStatus":"accepted"},{"email":"14aisypova65@gmail.com","responseStatus":"accepted"},{"email":"mksmabdulhalikov@gmail.com","responseStatus":"accepted"},{"email":"rustam19920295@gmail.com","responseStatus":"accepted"},{"email":"galinazeleznak47352@gmail.com","responseStatus":"accepted"},{"email":"ivan.olegovich90@gmail.com","responseStatus":"accepted"},{"email":"zhamsaranova1981@gmail.com","responseStatus":"accepted"},{"email":"timurshestnii@gmail.com","responseStatus":"accepted"},{"email":"spartak131666@gmail.com","responseStatus":"accepted"},{"email":"Sergeiterentev10012017@gmail.com","responseStatus":"accepted"},{"email":"nekrasov.nikolay.55@gmail.com","responseStatus":"accepted"},{"email":"fiplfiplfipl@gmail.com","responseStatus":"accepted"},{"email":"erdeneev17@gmail.com","responseStatus":"accepted"},{"email":"scarbrough38@gmail.com","responseStatus":"accepted"},{"email":"yfvfyufy1962@gmail.com","responseStatus":"accepted"},{"email":"sirius.800.nwb@gmail.com","responseStatus":"accepted"},{"email":"turniikman@gmail.com","responseStatus":"accepted"},{"email":"asurkov1234@gmail.com","responseStatus":"accepted"},{"email":"wovan03tany03@gmail.com","responseStatus":"accepted"},{"email":"elmurzaev901@gmail.com","responseStatus":"accepted"},{"email":"79977821280q@gmail.com","responseStatus":"accepted"},{"email":"Rusbatkovich@gmail.com","responseStatus":"accepted"},{"email":"Figlot.Gitler@gmail.com","responseStatus":"accepted"},{"email":"sirius.888.nwb@gmail.com","responseStatus":"accepted"}],"visibility":"public","guestsCanSeeOtherGuests":false,"guestsCanModify":false,"guestsCanInviteOthers":true,"anyoneCanAddSelf":true,"reminders":{"useDefault":false,"overrides":[{"method":"email","minutes":60},{"method":"popup","minutes":15},{"method":"popup","minutes":60},{"method":"popup","minutes":1440},{"method":"popup","minutes":2880}]}}