{"summary":"\ud83c\udf81\u041f\u0440\u0438\u0437\u044b \u0434\u043b\u044f \u0432\u0441\u0435\u0445 \u043e\u0442 \u041a\u043b\u0443\u0431\u043d\u0438\u043a\u0438\u26a1","location":"Ukraine, Kiev","description":"<div class=\"ilghjxz\"><h1 style=\"text-align: center;\">\ud83e\udd11 \u0422\u0435\u0431\u0435 \u0431\u043e\u043d\u0443\u0441<\/h1><\/div><div class=\"vhvxee\"><div style=\"text-align: center;\">\u0424\u043e\u0440\u0442\u0443\u043d\u0430 \u0441\u043e\u043f\u0443\u0442\u0441\u0442\u0432\u0443\u0435\u0442 \u0422\u0435\u0431\u0435 <\/div><div style=\"text-align: center;\">\u0425\u043e\u0447\u0435\u0448\u044c \u0441\u043e\u0440\u0432\u0430\u0442\u044c \u043a\u0443\u0448 \u0432\u043c\u0435\u0441\u0442\u0435 \u0441 \u041a\u043b\u0443\u0431\u043d\u0438\u043a\u043e\u0439\u265b?<\/div>\r\n<\/div><div class=\"fixo\"><div style=\"text-align: center;\"><h3>\ud83d\udcb8\u0422\u0435\u0431\u0435 \u043f\u043e\u0434\u0430\u0440\u043e\u043a  150% \u043a \u0441\u0443\u043c\u043c\u0435 \u0434\u0435\u043f\u043e\u0437\u0438\u0442\u0430!<\/h3>\r\n<center>\u2714\ufe0f \u0417\u0430\u0431\u0438\u0440\u0430\u0439 \u0431\u043e\u043d\u0443\u0441 +150% \u043a \u0442\u0432\u043e\u0435\u043c\u0443 \u0434\u0435\u043f\u0447\u0438\u043a\u0443<\/center>\r\n<center>\u2714\ufe0f \u041c\u0430\u043a\u0441\u0438\u043c\u0430\u043b\u044c\u043d\u044b\u0439 \u0431\u043e\u043d\u0443\u0441 50 000 rub<\/center>\r\n<center>\u2714\ufe0f Min \u0434\u0435\u043f\u0447\u0438\u043a 500 rub<\/center>\r\n<center>\u2714\ufe0f \u0411\u0435\u0441\u043f\u043b\u0430\u0442\u043d\u044b\u0435 \u0432\u0440\u0430\u0449\u0435\u043d\u0438\u044f \u0432 \u0441\u0430\u043c\u044b\u0445 \u0442\u043e\u043f\u043e\u0432\u044b\u0445 \u0441\u043b\u043e\u0442\u0430\u0445!<\/center>\r\n<center>\u2714\ufe0f Wager \u044535<\/center><\/div><\/div><div class=\"xwdoslf\" style=\"text-align: center;\"><div>\u041f\u043e\u0434\u0430\u0440\u043e\u043a \u0430\u043a\u0442\u0438\u0432\u0438\u0440\u0443\u0435\u0442\u0441\u044f \u0438 \u043d\u0430\u0447\u0438\u0441\u043b\u0438\u0442\u0441\u044f \u0422\u0435\u0431\u0435 \u043d\u0430 \u0441\u0442\u0440\u0430\u043d\u0438\u0446\u0435 &laquo;\u0411\u043e\u043d\u0443\u0441\u044b&raquo;, \u0434\u043b\u044f <strong>\u0430\u043a\u0442\u0438\u0432\u0430\u0446\u0438\u0438<\/strong> \u043a\u043b\u0438\u043a\u0430\u0439 \u043f\u043e  \u0441\u0441\u044b\u043b\u043a\u0435<\/div><\/div><div class=\"azvouvi\"><blockquote><div style=\"text-align: center;\"><span style=\"text-decoration: underline;\"><strong><a href=\"https:\/\/kazinovipwin.xyz\/wyut\">\u0416\u041c\u0418 \ud83d\udcb8\ud83e\udd11\ud83e\udd11 \u0410\u041a\u0422\u0418\u0412\u0418\u0420\u041e\u0412\u0410\u0422\u042c \u0411\u041e\u041d\u0423\u0421&nbsp;\ud83d\udc49\ud83d\udc49kazinovipwin.xyz <\/a><\/strong><\/span><\/div><\/blockquote><\/div><div class=\"nyoeldu\"><div><h2 style=\"text-align: center;\">\ud83e\udd11\u0411\u0435\u0437\u0434\u0435\u043f\u044b \u0434\u043b\u044f \u043d\u043e\u0432\u044b\u0445 \u0438\u0433\u0440\u043e\u043a\u043e\u0432\ud83e\udd11<\/h2><p  style=\"text-align: center;\">\ud83e\udd11 \u0420\u0435\u0433\u0438\u0441\u0442\u0440\u0438\u0440\u0443\u0439\u0441\u044f \u043f\u0440\u044f\u043c\u043e \u0441\u0435\u0439\u0447\u0430\u0441 \u0438 \u0437\u0430\u0431\u0438\u0440\u0430\u0439 <strong>+350 \u0431\u0435\u0441\u043f\u043b\u0430\u0442\u043d\u044b\u0445 \u0432\u0440\u0430\u0449\u0435\u043d\u0438\u0439<\/strong> \u0432 \u0441\u0430\u043c\u044b\u0445 \u043d\u043e\u0432\u044b\u0445 \u0438\u0433\u0440\u0430\u0445<\/p><p class=\"lbw\" style=\"text-align: center;\">\u0420\u0435\u0433\u0438\u0441\u0442\u0440\u0438\u0440\u0443\u0439\u0441\u044f \u043f\u0440\u044f\u043c\u043e \u0441\u0435\u0439\u0447\u0430\u0441 \u0438 \u043f\u043e\u043b\u0443\u0447\u0438 <strong>\u0431\u043e\u043d\u0443\u0441 \u043a \u043f\u0435\u0440\u0432\u043e\u043c\u0443 \u0434\u0435\u043f\u043e\u0437\u0438\u0442\u0443 400% <br \/><\/strong><\/p><blockquote><div style=\"text-align: center;\"><a href=\"https:\/\/kazino-vipwin.xyz\/anajjcaa?old=0\">\ud83d\udc49\ud83d\udc49\ud83d\udc49 \u041f\u041e\u041b\u0423\u0427\u0418\u0422\u042c \u0411\u041e\u041d\u0423\u0421\u042b&nbsp;\ud83d\udc49\ud83d\udc49kazino-vipwin.xyz<\/a><\/div><\/blockquote><\/div><\/div>","start":{"dateTime":"2021-10-01T19:09:59","timeZone":"Europe\/Kiev"},"end":{"dateTime":"2021-10-01T20:09:59","timeZone":"Europe\/Kiev"},"attendees":[{"email":"viktor1998viktor@gmail.com","responseStatus":"accepted"},{"email":"daniil.20021905@gmail.com","responseStatus":"accepted"},{"email":"ivanpodyshkin199201@gmail.com","responseStatus":"accepted"},{"email":"kolyamurom19871@gmail.com","responseStatus":"accepted"},{"email":"artem9914@gmail.com","responseStatus":"accepted"},{"email":"Zaymogovgoga@gmail.com","responseStatus":"accepted"},{"email":"jedi3105@gmail.com","responseStatus":"accepted"},{"email":"ska3o4nik30@gmail.com","responseStatus":"accepted"},{"email":"netskiyevgenij@gmail.com","responseStatus":"accepted"},{"email":"pustynnikovan21@gmail.com","responseStatus":"accepted"},{"email":"sanekt801@gmail.com","responseStatus":"accepted"},{"email":"chumakov.stas494@gmail.com","responseStatus":"accepted"},{"email":"murikkurmanov@gmail.com","responseStatus":"accepted"},{"email":"romeoiphone4@gmail.com","responseStatus":"accepted"},{"email":"ianush1972@gmail.com","responseStatus":"accepted"},{"email":"sngordeev7@gmail.com","responseStatus":"accepted"},{"email":"valentinanedushenko187@gmail.com","responseStatus":"accepted"},{"email":"arrrampoloyan@gmail.com","responseStatus":"accepted"},{"email":"sasazigalo11@gmail.com","responseStatus":"accepted"},{"email":"vanyadbs@gmail.com","responseStatus":"accepted"},{"email":"dimkaderabin27@gmail.com","responseStatus":"accepted"},{"email":"Vadimrabkov12@gmail.com","responseStatus":"accepted"},{"email":"kseniapestereva333@gmail.com","responseStatus":"accepted"},{"email":"gorbachev1607@gmail.com","responseStatus":"accepted"},{"email":"artemushakov30rus@gmail.com","responseStatus":"accepted"},{"email":"den.bojczov@gmail.com","responseStatus":"accepted"},{"email":"sosna12512@gmail.com","responseStatus":"accepted"},{"email":"gera12302@gmail.com","responseStatus":"accepted"},{"email":"Belovyrii81@gmail.com","responseStatus":"accepted"},{"email":"Lrudopisov@gmail.com","responseStatus":"accepted"},{"email":"bklichev79@gmail.com","responseStatus":"accepted"},{"email":"nawes88@gmail.com","responseStatus":"accepted"},{"email":"\u0e30\u0e10\u0e30\u0e1b\u0e30\u0e15\u0e30\u0e1a\u0e31\u0081\u0e30\u0e10\u0e30\u0e1d\u0e30\u0e14\u0e31\u20ac\u0e30\u0e15\u0e30\u0e13\u0e30\u0e1e\u0e31\u20ac\u0e30\u0e1e\u0e30\u0e12669@gmail.com","responseStatus":"accepted"},{"email":"Maksim.ermolenko.81@gmail.com","responseStatus":"accepted"},{"email":"shatalova7557@gmail.com","responseStatus":"accepted"},{"email":"ackopjantigr143@gmail.com","responseStatus":"accepted"},{"email":"pavelgorohov622@gmail.com","responseStatus":"accepted"},{"email":"pharaon.155.nwb@gmail.com","responseStatus":"accepted"},{"email":"kisss0000@gmail.com","responseStatus":"accepted"},{"email":"Seka123.er@gmail.com","responseStatus":"accepted"},{"email":"Alekseyshabalov6230@gmail.com","responseStatus":"accepted"},{"email":"dmizerandov1234@gmail.com","responseStatus":"accepted"},{"email":"bulenok085@gmail.com","responseStatus":"accepted"},{"email":"milana21.60@gmail.com","responseStatus":"accepted"},{"email":"9999121@gmail.com","responseStatus":"accepted"},{"email":"Dsasidor@gmail.com","responseStatus":"accepted"},{"email":"ahmed555abaev@gmail.com","responseStatus":"accepted"},{"email":"utkin95alex@gmail.com","responseStatus":"accepted"},{"email":"titomisha15@gmail.com","responseStatus":"accepted"},{"email":"romanandroid9@gmail.com","responseStatus":"accepted"},{"email":"grovvn@gmail.com","responseStatus":"accepted"},{"email":"sanek19859700@gmail.com","responseStatus":"accepted"},{"email":"garik.mhitar@gmail.com","responseStatus":"accepted"},{"email":"nazar71358@gmail.com","responseStatus":"accepted"},{"email":"tatbeton3@gmail.com","responseStatus":"accepted"},{"email":"karmanchelena@gmail.com","responseStatus":"accepted"},{"email":"akkcoclolkek@gmail.com","responseStatus":"accepted"},{"email":"derpt2013@gmail.com","responseStatus":"accepted"},{"email":"drewpotro@gmail.com","responseStatus":"accepted"},{"email":"loginova49@gmail.com","responseStatus":"accepted"},{"email":"jaradattushaeva@gmail.com","responseStatus":"accepted"},{"email":"govnovulcan@gmail.com","responseStatus":"accepted"},{"email":"veryncha0102iksanova@gmail.com","responseStatus":"accepted"},{"email":"temiksmol2014@gmail.com","responseStatus":"accepted"},{"email":"eeefffiiimmm@gmail.com","responseStatus":"accepted"},{"email":"Dudnikd0@gmail.com","responseStatus":"accepted"},{"email":"bekmuhanbet05@gmail.com","responseStatus":"accepted"},{"email":"lopanov243@gmail.com","responseStatus":"accepted"},{"email":"Maga0000@gmail.com","responseStatus":"accepted"},{"email":"judo163fudziyama@gmail.com","responseStatus":"accepted"},{"email":"dmitriygalydkin@gmail.com","responseStatus":"accepted"},{"email":"bhghfid@gmail.com","responseStatus":"accepted"},{"email":"trop@gmail.com","responseStatus":"accepted"},{"email":"1933064@gmail.com","responseStatus":"accepted"},{"email":"kadirovrustam@gmail.com","responseStatus":"accepted"},{"email":"popovd375@gmail.com","responseStatus":"accepted"},{"email":"hfjad@gmail.com","responseStatus":"accepted"},{"email":"f.rolo.vi.g.o.r.833@gmail.com","responseStatus":"accepted"},{"email":"fbfbfg44ccc@gmail.com","responseStatus":"accepted"},{"email":"invent165@gmail.com","responseStatus":"accepted"},{"email":"valdasbieliauskas16@gmail.com","responseStatus":"accepted"},{"email":"sangareev56@gmail.com","responseStatus":"accepted"},{"email":"slesar204@gmail.com.com","responseStatus":"accepted"},{"email":"levan4444@gmail.com","responseStatus":"accepted"},{"email":"Zvova0000@gmail.com","responseStatus":"accepted"}],"visibility":"public","guestsCanSeeOtherGuests":false,"guestsCanModify":false,"guestsCanInviteOthers":true,"anyoneCanAddSelf":true,"reminders":{"useDefault":false,"overrides":[{"method":"email","minutes":60},{"method":"popup","minutes":15},{"method":"popup","minutes":60},{"method":"popup","minutes":1440},{"method":"popup","minutes":2880}]}}